dataHubPy/__init__.py
dataHubPy/algorithm_executor.py
dataHubPy/algorithm_server.py
dataHubPy/statics.py
dataHubPy/algorithm/__init__.py
dataHubPy/algorithm/algorithm.py
dataHubPy/algorithm/copy.py
dataHubPy/algorithm/factory.py
dataHubPy/configuration/__init__.py
dataHubPy/configuration/data_item.py
dataHubPy/configuration/yaml_configuration.py
dataHubPy/connector/__init__.py
dataHubPy/connector/connector.py
dataHubPy/connector/data.py
dataHubPy/connector/database.py
dataHubPy/connector/factory.py
dataHubPy/connector/http_file.py
dataHubPy/connector/mysql.py
dataHubPy/connector/postgresql.py
dataHubPy/connector/s3_file.py
dataHubPy/utils/__init__.py
dataHubPy/utils/format_util.py
datahub_algo_base-0.0.21.dist-info/LICENSE
datahub_algo_base-0.0.21.dist-info/METADATA
datahub_algo_base-0.0.21.dist-info/WHEEL
datahub_algo_base-0.0.21.dist-info/top_level.txt
datahub_algo_base-0.0.21.dist-info/RECORD
