Metadata-Version: 2.1
Name: datahub-algo-base
Version: 0.0.21
Summary: A template for algorithm node
Home-page: https://gitea-ops.lab.zjvis.net/flint/data-hub
Author: Aaron
Author-email: byang628@zhejianglab.com
Classifier: Programming Language :: Python :: 3
Classifier: License :: OSI Approved :: MIT License
Classifier: Operating System :: OS Independent
Requires-Python: >=3.7
License-File: LICENSE
Requires-Dist: waitress
Requires-Dist: minio
Requires-Dist: numpy
Requires-Dist: pandas
Requires-Dist: Flask
Requires-Dist: requests
Requires-Dist: psycopg2
Requires-Dist: PyMySQL
Requires-Dist: PyYAML
Requires-Dist: scikit-learn
Requires-Dist: SQLAlchemy
Requires-Dist: impyute
